mapreader/__init__.py
mapreader/__main__.py
mapreader/_version.py
mapreader/annotate/__init__.py
mapreader/annotate/annotator.py
mapreader/classify/__init__.py
mapreader/classify/classifier.py
mapreader/classify/custom_models.py
mapreader/classify/datasets.py
mapreader/classify/load_annotations.py
mapreader/download/__init__.py
mapreader/download/data_structures.py
mapreader/download/downloader.py
mapreader/download/downloader_utils.py
mapreader/download/iiif_downloader.py
mapreader/download/sheet_downloader.py
mapreader/download/tile_loading.py
mapreader/download/tile_merging.py
mapreader/load/__init__.py
mapreader/load/geo_utils.py
mapreader/load/images.py
mapreader/load/loader.py
mapreader/process/__init__.py
mapreader/process/context_post_process.py
mapreader/process/occlusion_analysis.py
mapreader/process/process.py
mapreader/spot_text/__init__.py
mapreader/spot_text/dataclasses.py
mapreader/spot_text/deepsolo_runner.py
mapreader/spot_text/dptext_detr_runner.py
mapreader/spot_text/maptext_runner.py
mapreader/spot_text/runner_base.py
mapreader/utils/__init__.py
mapreader/utils/compute_and_save_stats.py
mapreader/utils/load_frames.py
mapreader/utils/slice_parallel.py
mapreader-1.8.2.dist-info/licenses/LICENSE
mapreader-1.8.2.dist-info/METADATA
mapreader-1.8.2.dist-info/WHEEL
mapreader-1.8.2.dist-info/entry_points.txt
mapreader-1.8.2.dist-info/top_level.txt
mapreader-1.8.2.dist-info/RECORD
