Metadata-Version: 2.4
Name: mapreader
Version: 1.8.2
Summary: A computer vision pipeline for the semantic exploration of maps/images at scale
Home-page: https://github.com/Living-with-machines/MapReader
Download-URL: https://github.com/Living-with-machines/MapReader/archive/refs/heads/main.zip
Author: MapReader team
License: MIT License
Keywords: Computer Vision,Classification,Deep Learning,living with machines
Platform: OS Independent
Classifier: Development Status :: 3 - Alpha
Classifier: License :: OSI Approved :: MIT License
Classifier: Natural Language :: English
Classifier: Programming Language :: Python :: 3.7
Classifier: Programming Language :: Python :: 3.8
Classifier: Intended Audience :: End Users/Desktop
Classifier: Intended Audience :: Developers
Classifier: Intended Audience :: Education
Classifier: Intended Audience :: Science/Research
Classifier: Operating System :: Unix
Classifier: Operating System :: Microsoft :: Windows
Classifier: Operating System :: MacOS
Classifier: Operating System :: OS Independent
Classifier: Topic :: Software Development
Classifier: Topic :: Software Development :: Libraries :: Python Modules
Classifier: Topic :: Scientific/Engineering :: Artificial Intelligence
Requires-Python: >=3.9
License-File: LICENSE
Requires-Dist: matplotlib<4.0.0,>=3.5.0
Requires-Dist: numpy<2.0.0,>=1.21.5
Requires-Dist: pandas>=2.0.0
Requires-Dist: pyproj<4.0.0,>=3.2.0
Requires-Dist: azure-storage-blob<13.0.0,>=12.9.0
Requires-Dist: aiohttp<4.0.0,>=3.8.1
Requires-Dist: Shapely<3.0.0,>=2.0.0
Requires-Dist: nest-asyncio<2.0.0,>=1.5.1
Requires-Dist: scikit-image>=0.18.3
Requires-Dist: scikit-learn<2.0.0,>=1.0.1
Requires-Dist: torch<=2.2.2,>=1.10.0
Requires-Dist: torchvision<=0.17.2,>=0.11.1
Requires-Dist: jupyter<2.0.0,>=1.0.0
Requires-Dist: ipykernel<7.0.0,>=6.5.1
Requires-Dist: ipywidgets<9.0.0,>=8.0.0
Requires-Dist: ipyannotate==0.1.0-beta.0
Requires-Dist: Cython<0.30.0,>=0.29.24
Requires-Dist: PyYAML<7.0,>=6.0
Requires-Dist: tensorboard<3.0.0,>=2.7.0
Requires-Dist: parhugin<0.0.4,>=0.0.3
Requires-Dist: geopy==2.1.0
Requires-Dist: rasterio<2.0.0,>=1.2.10
Requires-Dist: simplekml<2.0.0,>=1.3.6
Requires-Dist: versioneer>=0.28
Requires-Dist: tqdm<5.0.0
Requires-Dist: torchinfo<2.0.0
Requires-Dist: openpyxl<4.0.0,>=3.1.2
Requires-Dist: geopandas<1.0.0
Requires-Dist: pyogrio>=0.7.2
Requires-Dist: cartopy>=0.22.0
Requires-Dist: joblib>=1.4.0
Requires-Dist: opencv-python<5.0.0.0,>=4.8.1.78
Requires-Dist: folium<1.0.0,>=0.12
Requires-Dist: mapclassify<3.0.0,>=2.0.0
Requires-Dist: xyzservices==2024.9.0
Requires-Dist: piffle>=0.7.0
Requires-Dist: lxml
Provides-Extra: dev
Requires-Dist: pytest<9.0.0; extra == "dev"
Requires-Dist: pytest-cov<6.0.0,>=4.1.0; extra == "dev"
Requires-Dist: timm<1.0.0; extra == "dev"
Requires-Dist: transformers!=4.50.0,<4.51.3; extra == "dev"
Requires-Dist: black<25.0.0,>=23.7.0; extra == "dev"
Requires-Dist: flake8<8.0.0,>=6.0.0; extra == "dev"
Dynamic: author
Dynamic: classifier
Dynamic: description
Dynamic: description-content-type
Dynamic: download-url
Dynamic: home-page
Dynamic: keywords
Dynamic: license
Dynamic: license-file
Dynamic: platform
Dynamic: provides-extra
Dynamic: requires-dist
Dynamic: requires-python
Dynamic: summary
